jupyter_server_extension/__init__.py
jupyter_server_extension/_version.py
jupyter_server_extension/handlers.py
jupyter_server_extension/labextension/build_log.json
jupyter_server_extension/labextension/package.json
jupyter_server_extension/labextension/static/lib_index_js.10bf10430d6219207e84.js
jupyter_server_extension/labextension/static/lib_index_js.10bf10430d6219207e84.js.map
jupyter_server_extension/labextension/static/remoteEntry.b11656cf16c378c6c6ac.js
jupyter_server_extension/labextension/static/remoteEntry.b11656cf16c378c6c6ac.js.map
jupyter_server_extension/labextension/static/style.js
jupyter_server_extension/labextension/static/style_index_js.e7d12e1b132efd2e6862.js
jupyter_server_extension/labextension/static/style_index_js.e7d12e1b132efd2e6862.js.map
jupyter_server_extension/labextension/static/vendors-node_modules_css-loader_dist_runtime_api_js-node_modules_css-loader_dist_runtime_cssW-72eba1.1836539d6a34cf459a59.js
jupyter_server_extension/labextension/static/vendors-node_modules_css-loader_dist_runtime_api_js-node_modules_css-loader_dist_runtime_cssW-72eba1.1836539d6a34cf459a59.js.map
sister_jupyter_server_extension-0.1.0.data/data/share/jupyter/labextensions/sister-jupyter-server-extension/build_log.json
sister_jupyter_server_extension-0.1.0.data/data/share/jupyter/labextensions/sister-jupyter-server-extension/install.json
sister_jupyter_server_extension-0.1.0.data/data/share/jupyter/labextensions/sister-jupyter-server-extension/package.json
sister_jupyter_server_extension-0.1.0.data/data/share/jupyter/labextensions/sister-jupyter-server-extension/static/lib_index_js.10bf10430d6219207e84.js
sister_jupyter_server_extension-0.1.0.data/data/share/jupyter/labextensions/sister-jupyter-server-extension/static/lib_index_js.10bf10430d6219207e84.js.map
sister_jupyter_server_extension-0.1.0.data/data/share/jupyter/labextensions/sister-jupyter-server-extension/static/remoteEntry.b11656cf16c378c6c6ac.js
sister_jupyter_server_extension-0.1.0.dist-info/LICENSE
sister_jupyter_server_extension-0.1.0.dist-info/METADATA
sister_jupyter_server_extension-0.1.0.dist-info/WHEEL
sister_jupyter_server_extension-0.1.0.dist-info/top_level.txt
sister_jupyter_server_extension-0.1.0.dist-info/RECORD
